{
  "date": "2026-07-08",
  "items": [
    {
      "id": "2026-07-08-re-1",
      "date": "2026-07-08",
      "category": "realestate",
      "headline": "구윤철 부총리 \"부동산 세제개편안 7월 말 발표\" — 보유세·거래세 동시 손질",
      "preview": "구윤철 부총리 겸 기획재정부 장관이 7일 부동산 세제개편안을 이달 말 발표하겠다고 밝혔다. 보유세와 거래세를 함께 조정하는 방향으로 검토 중이며, \"집은 리빙(living)이지 바잉(buying)이 아니다\"는 원칙 아래 실거주자 보호·투기 차단을 기본 방향으로 삼겠다고 강조했다. 발표에 앞서 국민 의견을 수렴하는 절차를 거칠 예정이다.",
      "body": "구윤철 부총리 겸 기획재정부 장관은 7일 부동산 세제개편안 발표 시기와 관련해 \"7월 말 정도로 생각하고 있다\"고 밝혔다. 보유세와 거래세를 동시에 손질하느냐는 질문에는 \"두 가지가 밸런스를 이뤄야 한다. 그런 차원에서 함께 보고 있다\"고 답했다.\n\n개편의 기본 원칙으로는 실거주자 중심의 주택시장 확립을 제시했다. 구 부총리는 \"기본적으로 집은 바잉(buying)이 아니고 리빙(living)을 위한 것이라는 원칙 하에 세제를 보고 있다\"며 실거주 1주택자는 보호하되 비거주·투기 목적 보유자에게는 세 부담을 높이는 방향을 시사했다.\n\n정부는 세제개편안 발표 전 국민 의견 수렴 절차를 밟겠다고 밝혔다. 구 부총리는 \"정부가 일방적으로 결정하기보다는 폭넓게 국민들의 의견을 경청하고 최대한 반영하겠다\"고 말했다.",
      "source": "파이낸셜뉴스",
      "source_url": "https://www.fnnews.com/news/202607071240453153",
      "lang_original": "ko"
    },
    {
      "id": "2026-07-08-re-2",
      "date": "2026-07-08",
      "category": "realestate",
      "headline": "이재명 대통령 '불로소득 공화국 탈피' 천명 — 지방선거 후 부동산 강공 드라이브",
      "preview": "이재명 대통령이 지방선거 이후 부동산 시장에 강력한 정책 드라이브를 걸겠다고 예고했다. \"불로소득 공화국을 반드시 탈출하겠다\"는 의지를 천명하며 보유세 강화 등 강경 기조를 유지하겠다고 강조했다. 정부는 세제 개편과 공급 확대 대책을 조율해 조만간 발표할 방침이다.",
      "body": "이재명 대통령은 지방선거 후 부동산 투기 근절을 위한 강공 드라이브를 예고하며 \"불로소득 공화국을 반드시 탈출하겠다\"고 천명했다. 보유세 등 세제를 강화하는 방향의 부동산 정책을 지속 추진하겠다는 의지를 거듭 밝혔다.\n\n앞서 이 대통령은 취임 1주년 기자회견에서 보유세 관련 세제 문제를 7월 중 정리해 발표하겠다고 예고했으며, 공급 대책에 대해서도 \"속도를 빨리 내서 조만간 발표할 것\"이라고 밝혔다. 임대주택 공급과 관련해서는 \"싸게, 좋은 곳에, 평범한 중산층이 충분히 살 수 있는 좋은 품질로 공급하겠다\"고 강조했다.\n\n정부는 2026년부터 2030년까지 수도권에 총 135만 호(연간 27만 호)의 신규 주택을 공급한다는 계획도 발표한 바 있으며, 국무총리 소속 부동산감독원(가칭)을 설립해 시장교란 행위에 대한 대응도 강화할 예정이다.",
      "source": "MBC 뉴스",
      "source_url": "https://imnews.imbc.com/replay/2026/nwdesk/article/6826852_37004.html",
      "lang_original": "ko"
    },
    {
      "id": "2026-07-08-re-3",
      "date": "2026-07-08",
      "category": "realestate",
      "headline": "서울 전세 씨 말라 — 무주택·젊은층 경기 외곽으로 밀려나",
      "preview": "서울 전세 시장의 공급 부족이 심화되면서 무주택자와 젊은층이 경기·인천 등 수도권 외곽으로 밀려나고 있다. 서울 전세 매물은 1년 새 25% 줄었고, 30평대 전세 보증금은 6억 9,000만 원으로 전년 대비 8% 올랐다. 6월 전세수급지수는 5년 6개월 만에 가장 나쁜 수준을 기록했다.",
      "body": "서울 아파트 전세 공급 부족이 장기화되면서 무주택 서민과 젊은층이 경기·인천 등 수도권 외곽으로 이주하는 현상이 뚜렷해지고 있다. 서울 시내 전세 매물 수는 1년 사이 25%나 줄었으며, 6월 둘째 주 전세수급지수는 5년 6개월 만에 최악 수준으로 악화됐다.\n\n전세 보증금도 빠르게 오르고 있다. 서울 30평대 기준 전세 보증금은 6억 9,000만 원으로 전년 대비 8% 상승했다. 올해 1월 신규 계약과 갱신 계약 간 보증금 격차는 4,375만 원이었지만, 6월에는 8,000만 원으로 두 배 가까이 확대됐다.\n\n최근 3년간 서울에서 다른 지역으로 전출한 인구 139만 9,645명 중 84만 6,321명(60.5%)이 경기도로 이동했으며, 이주 이유 1위가 '주택'(32.64%)이었다. 전문가들은 하반기에도 서울 전세 공급 부족이 지속될 것으로 전망하고 있다.",
      "source": "MBC 뉴스투데이",
      "source_url": "https://imnews.imbc.com/replay/2026/nwtoday/article/6832435_37012.html",
      "lang_original": "ko"
    },
    {
      "id": "2026-07-08-re-4",
      "date": "2026-07-08",
      "category": "realestate",
      "headline": "7월 전국 아파트 입주물량 증가 전환 — 하반기 수도권 전세 시장 '분수령'",
      "preview": "7월부터 전국 아파트 입주물량이 전월 대비 증가세로 돌아서면서 하반기 수도권 전세 시장의 분수령이 될지 주목된다. 상반기 내내 공급 부족으로 전세가가 급등했던 만큼, 7월 이후 입주 물량 증가가 시장 안정으로 이어질지 관건이다. 다만 서울 내 신규 분양·재건축 물량은 여전히 제한적이어서 근본적인 해소에는 시간이 필요하다는 분석이다.",
      "body": "7월부터 전국 아파트 입주물량이 전월 대비 증가세로 전환되는 것으로 나타나면서, 상반기 내내 공급 부족에 시달렸던 수도권 전세 시장이 하반기에 숨통이 트일지 주목된다.\n\n상반기에는 서울 아파트 전세 매물이 1년 새 25% 줄어들고, 전세수급지수가 5년 6개월 만에 최악 수준으로 악화되는 등 공급 부족이 심각했다. 2025년 서울 아파트 입주 물량이 전년 대비 약 25% 감소한 영향이 올해까지 이어지고 있다는 분석이다.\n\n전문가들은 하반기 입주 물량 증가가 전세 가격 상승 속도를 늦출 수 있는 변수가 될 것으로 보면서도, 서울 내 신규 분양·재건축 물량이 여전히 제한적이어서 근본적인 공급 부족 해소에는 상당한 시간이 필요하다고 분석하고 있다.",
      "source": "더퍼블릭",
      "source_url": "https://www.thepublic.kr/news/articleView.html?idxno=308516",
      "lang_original": "ko"
    },
    {
      "id": "2026-07-08-econ-5",
      "date": "2026-07-08",
      "category": "economy",
      "headline": "미 연준 FOMC 6월 의사록 오늘 오후 공개 — 워시 의장 점도표 침묵·9인 매파 논거 주목",
      "preview": "미국 연방준비제도(Fed)가 8일(현지시간) 오후 2시 6월 연방공개시장위원회(FOMC) 의사록을 공개한다. 6월 회의에서 18명 중 9명이 연내 추가 금리 인상을 지지했으며, 케빈 워시 의장이 2012년 이후 처음으로 금리 전망치를 제출하지 않아 그 배경이 의사록을 통해 밝혀질지 관심이 쏠린다. 선물시장은 9월 금리 인상 가능성을 58%로 반영하고 있다.",
      "body": "미국 연방준비제도(Fed)는 8일(현지시간) 오후 2시(미 동부 기준) 지난 6월 16~17일 열린 연방공개시장위원회(FOMC) 의사록을 공개할 예정이다. 이번 의사록은 6월 회의에서 나타난 매파적(hawkish) 전환의 내부 논거를 더 자세히 보여줄 것으로 기대된다.\n\n6월 회의에서 FOMC는 기준금리(policy rate)를 현 수준인 3.50%~3.75%로 동결했다. 그러나 점도표(dot plot)에서 18명의 참가 위원 중 9명이 연내 추가 인상을 지지했고, 2026년 말 기준금리 중간값이 3.8%로 상향 조정됐다. 2026년 개인소비지출(PCE) 물가 전망도 3.6%로 높아졌으며, GDP 성장률 전망은 2.2%로 하향됐다.\n\n특히 케빈 워시(Kevin Warsh) 신임 의장은 2012년 점도표 제도 도입 이후 처음으로 자신의 금리 전망치를 제출하지 않아 시장의 관심을 끌었다. 의사록을 통해 이에 대한 배경 설명과 함께 각 위원의 금리 경로에 관한 세부 논의 내용이 공개될 전망이다. 선물(futures) 시장은 현재 9월 금리 인상 가능성을 58%로 반영하고 있다.",
      "source": "TechTimes",
      "source_url": "https://www.techtimes.com/articles/319827/20260707/fed-minutes-due-wednesday-nine-hawkish-dots-warshs-deliberate-silence.htm",
      "lang_original": "en"
    },
    {
      "id": "2026-07-08-econ-6",
      "date": "2026-07-08",
      "category": "economy",
      "headline": "SpaceX 나스닥-100 첫 합류 — 삼성전자 AI 실적 실망에 기술주 동반 하락",
      "preview": "스페이스X(SpaceX)가 7일(현지시간) 나스닥-100(Nasdaq-100) 지수에 편입됐지만, 같은 날 삼성전자의 인공지능(AI) 관련 실적이 시장 기대에 못 미치면서 기술주 전반이 약세를 보였다. 나스닥은 약 1% 하락했으며, S&P 500도 0.13% 내렸다. 스페이스X는 기업공개(IPO) 15거래일 만에 나스닥-100에 편입된 첫 사례다.",
      "body": "일론 머스크(Elon Musk)의 우주·통신 기업 스페이스X(SpaceX)가 7일(현지시간) 나스닥-100(Nasdaq-100) 지수에 공식 편입됐다. 나스닥이 6월 26일 발표한 '패스트 트랙(fast-track)' 신규 규정에 따라 기업공개(IPO, Initial Public Offering) 후 15거래일 만에 편입된 첫 사례다. 약 8,000억 달러 규모의 지수 추종 펀드·상장지수펀드(ETF)가 자동으로 스페이스X 주식을 매입해야 하며, JP모건(JPMorgan)은 자동 매수 규모를 약 43억 달러로 추산했다.\n\n그러나 같은 날 삼성전자가 발표한 2분기 실적이 인공지능(AI) 부문의 높은 기대치에 미치지 못하면서 기술주 전반에 부정적 영향을 미쳤다. 삼성전자 한국 주가는 7% 가까이 하락해 코스피(KOSPI) 지수를 끌어내렸으며, 이 여파가 미국 시장으로 번지면서 나스닥은 약 1%, S&P 500은 0.13% 하락했다. 기술 섹터(Technology Sector) 관련 ETF는 장 초반 약 2.2% 빠졌다.\n\n전날(6일) 다우존스 산업평균지수(Dow Jones Industrial Average)는 53,055.91포인트로 사상 최고치를 기록한 바 있다.",
      "source": "TheStreet",
      "source_url": "https://www.thestreet.com/stock-market-today/stock-market-today-dow-jones-sp-500-nasdaq-updates-july-7-2026",
      "lang_original": "en"
    },
    {
      "id": "2026-07-08-econ-7",
      "date": "2026-07-08",
      "category": "economy",
      "headline": "미국 비트코인 현물 ETF, 10일 연속 유출 종료 — 하루 2억 2,170만 달러 순유입",
      "preview": "미국에 상장된 비트코인(Bitcoin) 현물 상장지수펀드(ETF)가 3일(현지시간) 2억 2,170만 달러 순유입을 기록하며 10거래일 연속 유출 행진을 끝냈다. 10일간 누적 유출액은 27억 달러에 달했다. 피델리티(Fidelity)의 FBTC가 1억 6,600만 달러를 끌어들여 당일 유입을 주도했다.",
      "body": "미국에 상장된 비트코인(Bitcoin) 현물 ETF(Exchange-Traded Fund) 상품군이 3일(현지시간) 2억 2,170만 달러 순유입을 기록하며 10거래일 연속 유출 행진을 마감했다. 약 2개월 만의 최대 단일 일 유입 규모다.\n\n앞선 10일간 누적 유출액은 27억 달러에 달했으며, 6월 한 달 동안에만 약 45억 달러가 빠져나갔다. 이 중 블랙록(BlackRock)의 IBIT가 6월 전체 유출의 약 75%를 차지했다. 고용 지표 부진으로 연방준비제도(Fed)의 금리 인상 우려가 완화된 것이 반전의 배경으로 분석된다.\n\n당일 피델리티(Fidelity)의 FBTC가 1억 6,600만 달러 유입으로 선두를 달린 반면, 블랙록 IBIT는 4,043만 달러 유출을 기록했다. 비트코인 가격은 7일 기준 6만 3,959달러로 24시간 대비 0.52% 상승했으며, 시가총액은 1조 2,800억 달러에 달한다.",
      "source": "CoinDesk",
      "source_url": "https://www.coindesk.com/markets/2026/07/03/finally-usd221-million-flow-into-bitcoin-etfs-ending-a-painful-10-day-outflow-streak",
      "lang_original": "en"
    },
    {
      "id": "2026-07-08-econ-8",
      "date": "2026-07-08",
      "category": "economy",
      "headline": "트럼프 전략 비트코인 준비금 표류 — 재무부·상무부 법적 갈등, 의회 입법도 공백",
      "preview": "도널드 트럼프(Donald Trump) 미국 대통령의 전략 비트코인 준비금(Strategic Bitcoin Reserve) 구축 계획이 재무부(Treasury)와 상무부(Commerce) 간 법적 관할권 갈등으로 진전을 보지 못하고 있다. 정부 보유 30만 BTC(시가 약 210억 달러) 관리 주체를 두고 부처가 맞서고 있으며, 의회 입법도 지연되고 있다.",
      "body": "도널드 트럼프(Donald Trump) 미국 대통령의 전략 비트코인 준비금(Strategic Bitcoin Reserve) 구축 계획이 부처 간 법적 갈등으로 표류하고 있다고 블룸버그(Bloomberg)가 6일(현지시간) 보도했다. 연방 정부가 자산 압수·몰수 등으로 확보한 30만 BTC 이상(시가 약 210억 달러)의 관리 주체를 재무부(Treasury Department)와 상무부(Commerce Department)가 서로 차지하려 경쟁하고 있다.\n\n미국 법무부(DOJ, Department of Justice) 산하 법률자문실(OLC, Office of Legal Counsel)은 \"재무부와 상무부 양 부처와 협력해 전략 비트코인 준비금 정책을 이행하기 위해 법적으로 사용 가능한 옵션을 결정하고 있다\"고 밝혔다. 그러나 어느 부처가 법적 관할권을 갖는지에 대한 결론은 내려지지 않은 상태다.\n\n트럼프 대통령은 2025년 3월 행정명령으로 전략 비트코인 준비금 설립을 지시했다. 백악관 암호화폐(crypto) 보좌관 패트릭 위트(Patrick Witt)는 4월 수 주 내에 다음 단계를 발표하겠다고 예고했으나 아직 공식 업데이트가 없다. 최종 계획 이행에는 의회 입법이 필요하다는 지적이 있으나 관련 법안은 구체적 진전을 보지 못하고 있다.",
      "source": "Bloomberg",
      "source_url": "https://www.bloomberg.com/news/articles/2026-07-06/trump-bitcoin-reserve-faces-hurdles-as-departments-seek-control",
      "lang_original": "en"
    },
    {
      "id": "2026-07-08-econ-9",
      "date": "2026-07-08",
      "category": "economy",
      "headline": "미국 6월 고용 5만 7,000명 증가 — 예상치 절반 하회, 실업률 4.2%",
      "preview": "미국 노동부가 2일(현지시간) 발표한 6월 고용보고서에 따르면 비농업 신규 일자리가 5만 7,000명 증가에 그쳐 시장 예상치 11만 5,000명을 크게 밑돌았다. 실업률은 4.2%로 전달보다 소폭 내렸지만, 노동력 참가율은 61.5%로 2021년 3월 이후 최저치를 기록했다. 이번 부진한 지표로 연방준비제도의 추가 금리 인상 우려는 다소 완화됐다는 평가다.",
      "body": "미국 노동부 노동통계국(BLS, Bureau of Labor Statistics)이 2일(현지시간) 발표한 6월 고용 동향(Employment Situation)에 따르면 비농업 부문 신규 고용은 5만 7,000명에 그쳐 시장 예상치 11만 5,000명을 크게 밑돌았다. 5월 수치도 12만 9,000명으로 하향 수정됐으며, 4월과 5월이 각각 3만 1,000명, 4만 3,000명씩 하향 조정되면서 최근 몇 달간의 고용 증가세가 당초 보고된 것보다 훨씬 약했던 것으로 나타났다.\n\n실업률(unemployment rate)은 4.2%로 전달 4.3%보다 소폭 내렸지만, 노동력 참가율(labor force participation rate)이 61.5%로 0.3%포인트 하락해 2021년 3월 이후 최저치를 기록했다. 가계 조사 기준으로는 취업자가 50만 7,000명 줄어들며 실업률 하락에 영향을 미쳤다.\n\n업종별로는 전문·사업 서비스(+3만 6,000명), 사회적 지원(+2만 5,000명), 의료(+2만 2,000명)가 증가했으나 레저·숙박업이 6만 1,000명 감소해 전체를 끌어내렸다. 제퍼리스(Jefferies)의 이코노미스트 토머스 사이먼스(Thomas Simons)는 \"고용 증가 속도의 둔화는 올해 금리 인상이 필요하지 않을 수 있음을 시사한다\"고 평가했다.",
      "source": "CNBC",
      "source_url": "https://www.cnbc.com/amp/2026/07/02/jobs-report-june-2026-.html",
      "lang_original": "en"
    },
    {
      "id": "2026-07-08-econ-10",
      "date": "2026-07-08",
      "category": "economy",
      "headline": "다우 53,000 돌파 사상 최고치 — S&P 500 상반기 9.4% 상승, 기업 실적 강세가 동력",
      "preview": "다우존스 산업평균지수(Dow Jones Industrial Average)가 6일(현지시간) 53,055.91포인트로 사상 최고치를 기록하며 3분기를 시작했다. S&P 500은 올해 들어 9.4%, 나스닥 종합지수는 12.5% 상승하며 2026년 상반기 강세를 이어갔다. 견조한 기업 실적과 소비 심리가 주요 동력으로 꼽혔다.",
      "body": "다우존스 산업평균지수(Dow Jones Industrial Average)가 6일(현지시간) 53,055.91포인트로 장을 마감하며 사상 최고치를 경신했다. S&P 500 지수는 7,537.43포인트, 나스닥 종합지수(Nasdaq Composite)는 26,121.16포인트를 기록했다. 연초 대비 S&P 500은 9.4%, 나스닥은 12.5%, 다우존스는 8.9% 각각 상승한 상태다.\n\n2026년 상반기 주가 강세의 주요 동력은 견조한 기업 이익과 소비 심리였다. 1월부터 5월까지 월평균 신규 고용은 약 11만 4,000명으로 노동 시장이 경기를 뒷받침했으며, 기업 실적도 예상치를 웃도는 경우가 많았다. 인공지능(AI) 투자 확대 기대감도 기술주 중심의 상승세에 기여했다.\n\n다만 6월 고용 부진(+5만 7,000명)과 연방준비제도(Fed)의 매파적 점도표(dot plot) 발표 이후 추가 금리 인상 가능성이 다시 부각되면서 하반기 시장 전망에는 불확실성이 남아 있다. 선물(futures) 시장은 9월 금리 인상 가능성을 약 58%로 반영하고 있다.",
      "source": "Yahoo Finance",
      "source_url": "https://ca.finance.yahoo.com/news/stock-market-today-monday-july-6-225645420.html",
      "lang_original": "en"
    }
  ]
}
